moonspic_codepacker/__init__.py
moonspic_codepacker-9.6.0.dist-info/METADATA
moonspic_codepacker-9.6.0.dist-info/WHEEL
moonspic_codepacker-9.6.0.dist-info/entry_points.txt
moonspic_codepacker-9.6.0.dist-info/top_level.txt
moonspic_codepacker-9.6.0.dist-info/RECORD
