Metadata-Version: 2.4
Name: moonspic-codepacker
Version: 9.6.0
Summary: Standalone code archival and integrity suite.
Author: MoonspicAI
Classifier: Programming Language :: Python :: 3
Classifier: License :: OSI Approved :: MIT License
Requires-Python: >=3.7
